{
   "id": 11,
   "name": "Transport",
   "imageName": "transport",
   "topics": [
      {
         "name": "Bicycles",
         "imageName": "transport-topic-1",
         "vocabularyItemIds": [
            "transport0",
            "transport1",
            "transport2",
            "transport3",
            "transport4",
            "transport5",
            "transport6",
            "transport7",
            "transport8",
            "transport9",
            "transport10",
            "transport11",
            "transport12",
            "transport13",
            "transport14"
         ]
      },
      {
         "name": "Boats",
         "imageName": "transport-topic-2",
         "vocabularyItemIds": [
            "transport15",
            "transport16",
            "transport17",
            "transport18",
            "transport19",
            "transport20",
            "transport21",
            "transport22",
            "transport23",
            "transport24",
            "transport25",
            "transport26",
            "transport27",
            "transport28",
            "transport29"
         ]
      },
      {
         "name": "Driving",
         "imageName": "transport-topic-3",
         "vocabularyItemIds": [
            "transport30",
            "transport31",
            "transport32",
            "transport33",
            "transport34",
            "transport35",
            "transport36",
            "transport37",
            "transport38",
            "transport39",
            "transport40",
            "transport41",
            "transport42",
            "transport43",
            "transport44"
         ]
      },
      {
         "name": "Road Signs",
         "imageName": "transport-topic-4",
         "vocabularyItemIds": [
            "transport45",
            "transport46",
            "transport47",
            "transport48",
            "transport49",
            "transport50",
            "transport51",
            "transport52",
            "transport53",
            "transport54",
            "transport55",
            "transport56",
            "transport57",
            "transport58",
            "transport59"
         ]
      },
      {
         "name": "Trains",
         "imageName": "transport-topic-5",
         "vocabularyItemIds": [
            "transport60",
            "transport61",
            "transport62",
            "transport63",
            "transport64",
            "transport65",
            "transport66",
            "transport67",
            "transport68",
            "transport69",
            "transport70",
            "transport71",
            "transport72",
            "transport73",
            "transport74"
         ]
      },
      {
         "name": "Transportation",
         "imageName": "transport-topic-6",
         "vocabularyItemIds": [
            "transport75",
            "transport76",
            "transport77",
            "transport78",
            "transport79",
            "transport80",
            "transport81",
            "transport82",
            "transport83",
            "transport84",
            "transport85",
            "transport86",
            "transport87",
            "transport88",
            "transport89"
         ]
      }
   ]
}
