 {
   "id": 8,
   "name": "Home",
   "imageName": "home",
   "topics": [
      {
         "name": "Bathroom",
         "imageName": "home-topic-1",
         "vocabularyItemIds": [
            "home0",
            "home1",
            "home2",
            "home3",
            "home4",
            "home5",
            "home6",
            "home7",
            "home8",
            "home9",
            "home10",
            "home11",
            "home12",
            "home13",
            "home14"
         ]
      },
      {
         "name": "Dining Room",
         "imageName": "home-topic-2",
         "vocabularyItemIds": [
            "home15",
            "home16",
            "home17",
            "home18",
            "home19",
            "home20",
            "home21",
            "home22",
            "home23",
            "home24",
            "home25",
            "home26",
            "home27",
            "home28",
            "home29"
         ]
      },
      {
         "name": "Home",
         "imageName": "home-topic-3",
         "vocabularyItemIds": [
            "home30",
            "home31",
            "home32",
            "home33",
            "home34",
            "home35",
            "home36",
            "home37",
            "home38",
            "home39",
            "home40",
            "home41",
            "home42",
            "home43",
            "home44"
         ]
      },
      {
         "name": "House",
         "imageName": "home-topic-4",
         "vocabularyItemIds": [
            "home45",
            "home46",
            "home47",
            "home48",
            "home49",
            "home50",
            "home51",
            "home52",
            "home53",
            "home54",
            "home55",
            "home56",
            "home57",
            "home58",
            "home59"
         ]
      },
      {
         "name": "Kitchen",
         "imageName": "home-topic-5",
         "vocabularyItemIds": [
            "home60",
            "home61",
            "home62",
            "home63",
            "home64",
            "home65",
            "home66",
            "home67",
            "home68",
            "home69",
            "home70",
            "home71",
            "home72",
            "home73",
            "home74"
         ]
      },
      {
         "name": "Materials",
         "imageName": "home-topic-6",
         "vocabularyItemIds": [
            "home75",
            "home76",
            "home77",
            "home78",
            "home79",
            "home80",
            "home81",
            "home82",
            "home83",
            "home84",
            "home85",
            "home86",
            "home87",
            "home88",
            "home89"
         ]
      }
   ]
}
